scsit/__init__.py
scsit/cfunction.so
scsit-1.0.5.data/scripts/scsit
scsit-1.0.5.dist-info/LICENSE
scsit-1.0.5.dist-info/METADATA
scsit-1.0.5.dist-info/WHEEL
scsit-1.0.5.dist-info/top_level.txt
scsit-1.0.5.dist-info/RECORD
