Metadata-Version: 2.1
Name: scsit
Version: 1.0.5
Summary: Biological gene analyse tool
Home-page: https://github.com/shang-qian/SCSit
Author: HNU_XIE_LAB
Author-email: susiew01@163.com
License: MIT
Keywords: scsit,scsit-tools
Platform: UNKNOWN
Requires-Python: >=2.7
License-File: LICENSE
